AUTHORS
ChangeLog
MANIFEST.in
README.rst
requirements.txt
setup.cfg
setup.py
leonardo_module_redactor/__init__.py
leonardo_module_redactor/settings.py
leonardo_module_redactor.egg-info/PKG-INFO
leonardo_module_redactor.egg-info/SOURCES.txt
leonardo_module_redactor.egg-info/dependency_links.txt
leonardo_module_redactor.egg-info/not-zip-safe
leonardo_module_redactor.egg-info/pbr.json
leonardo_module_redactor.egg-info/requires.txt
leonardo_module_redactor.egg-info/top_level.txt
leonardo_module_redactor/static/redactor/redactor.init.js
leonardo_module_redactor/static/redactor/redactor.js
leonardo_module_redactor/static/redactor/plugins/filemanager.js
leonardo_module_redactor/static/redactor/plugins/fontcolor.js
leonardo_module_redactor/static/redactor/plugins/fullscreen.js
leonardo_module_redactor/static/redactor/plugins/table.js
leonardo_module_redactor/static/redactor/plugins/textdirection.js
leonardo_module_redactor/static/redactor/plugins/video.js